{"meterId": "98125-1", "measurementInKWh": 5.622220492236797, "zipCode": 98125, "measurementDate": "2023-01-01T00:50:00"}
{"meterId": "98125-2", "measurementInKWh": 14.765184964415214, "zipCode": 98125, "measurementDate": "2023-01-01T00:50:00"}
{"meterId": "98125-3", "measurementInKWh": 17.54151299532534, "zipCode": 98125, "measurementDate": "2023-01-01T00:50:00"}
{"meterId": "98125-4", "measurementInKWh": 15.479620471559368, "zipCode": 98125, "measurementDate": "2023-01-01T00:50:00"}
{"meterId": "98126-1", "measurementInKWh": 17.348286879473093, "zipCode": 98126, "measurementDate": "2023-01-01T00:50:00"}
{"meterId": "98126-2", "measurementInKWh": 16.931470859562104, "zipCode": 98126, "measurementDate": "2023-01-01T00:50:00"}
{"meterId": "98126-3", "measurementInKWh": 18.764448602106235, "zipCode": 98126, "measurementDate": "2023-01-01T00:50:00"}
{"meterId": "98126-4", "measurementInKWh": 14.622707241582397, "zipCode": 98126, "measurementDate": "2023-01-01T00:50:00"}
{"meterId": "98133-1", "measurementInKWh": 13.56217185350154, "zipCode": 98133, "measurementDate": "2023-01-01T00:50:00"}
{"meterId": "98133-2", "measurementInKWh": 17.474051259720724, "zipCode": 98133, "measurementDate": "2023-01-01T00:50:00"}
{"meterId": "98133-3", "measurementInKWh": 10.401530282621096, "zipCode": 98133, "measurementDate": "2023-01-01T00:50:00"}
{"meterId": "98133-4", "measurementInKWh": 14.779493123316827, "zipCode": 98133, "measurementDate": "2023-01-01T00:50:00"}
{"meterId": "98134-1", "measurementInKWh": 19.234672988869775, "zipCode": 98134, "measurementDate": "2023-01-01T00:50:00"}
{"meterId": "98134-2", "measurementInKWh": 8.942626742011072, "zipCode": 98134, "measurementDate": "2023-01-01T00:50:00"}
{"meterId": "98134-3", "measurementInKWh": 17.18978600001227, "zipCode": 98134, "measurementDate": "2023-01-01T00:50:00"}
{"meterId": "98134-4", "measurementInKWh": 7.39376054584884, "zipCode": 98134, "measurementDate": "2023-01-01T00:50:00"}
{"meterId": "98136-1", "measurementInKWh": 13.654914879285712, "zipCode": 98136, "measurementDate": "2023-01-01T00:50:00"}
{"meterId": "98136-2", "measurementInKWh": 13.296861726940154, "zipCode": 98136, "measurementDate": "2023-01-01T00:50:00"}
{"meterId": "98136-3", "measurementInKWh": 14.258985522163757, "zipCode": 98136, "measurementDate": "2023-01-01T00:50:00"}
{"meterId": "98136-4", "measurementInKWh": 5.413213875936877, "zipCode": 98136, "measurementDate": "2023-01-01T00:50:00"}
{"meterId": "98144-1", "measurementInKWh": 16.697522431541127, "zipCode": 98144, "measurementDate": "2023-01-01T00:50:00"}
{"meterId": "98144-2", "measurementInKWh": 10.984214411503624, "zipCode": 98144, "measurementDate": "2023-01-01T00:50:00"}
{"meterId": "98144-3", "measurementInKWh": 8.481654950330391, "zipCode": 98144, "measurementDate": "2023-01-01T00:50:00"}
{"meterId": "98144-4", "measurementInKWh": 19.45710899905537, "zipCode": 98144, "measurementDate": "2023-01-01T00:50:00"}
{"meterId": "98146-1", "measurementInKWh": 8.414843014875903, "zipCode": 98146, "measurementDate": "2023-01-01T00:50:00"}
{"meterId": "98146-2", "measurementInKWh": 9.995025784114976, "zipCode": 98146, "measurementDate": "2023-01-01T00:50:00"}
{"meterId": "98146-3", "measurementInKWh": 13.874880969630363, "zipCode": 98146, "measurementDate": "2023-01-01T00:50:00"}
{"meterId": "98146-4", "measurementInKWh": 15.257360517753304, "zipCode": 98146, "measurementDate": "2023-01-01T00:50:00"}
{"meterId": "98148-1", "measurementInKWh": 12.024846705895957, "zipCode": 98148, "measurementDate": "2023-01-01T00:50:00"}
{"meterId": "98148-2", "measurementInKWh": 11.787816078787875, "zipCode": 98148, "measurementDate": "2023-01-01T00:50:00"}
{"meterId": "98148-3", "measurementInKWh": 12.572489162487031, "zipCode": 98148, "measurementDate": "2023-01-01T00:50:00"}
{"meterId": "98148-4", "measurementInKWh": 13.966185384913954, "zipCode": 98148, "measurementDate": "2023-01-01T00:50:00"}
{"meterId": "98154-1", "measurementInKWh": 19.973905046822217, "zipCode": 98154, "measurementDate": "2023-01-01T00:50:00"}
{"meterId": "98154-2", "measurementInKWh": 19.474955527192602, "zipCode": 98154, "measurementDate": "2023-01-01T00:50:00"}
{"meterId": "98154-3", "measurementInKWh": 18.309695089014987, "zipCode": 98154, "measurementDate": "2023-01-01T00:50:00"}
{"meterId": "98154-4", "measurementInKWh": 14.924301347660231, "zipCode": 98154, "measurementDate": "2023-01-01T00:50:00"}
{"meterId": "98155-1", "measurementInKWh": 6.501112911148649, "zipCode": 98155, "measurementDate": "2023-01-01T00:50:00"}
{"meterId": "98155-2", "measurementInKWh": 9.049438438110153, "zipCode": 98155, "measurementDate": "2023-01-01T00:50:00"}
{"meterId": "98155-3", "measurementInKWh": 16.444317476669582, "zipCode": 98155, "measurementDate": "2023-01-01T00:50:00"}
{"meterId": "98155-4", "measurementInKWh": 11.402969807741925, "zipCode": 98155, "measurementDate": "2023-01-01T00:50:00"}
{"meterId": "98125-1", "measurementInKWh": 6.232470832126769, "zipCode": 98125, "measurementDate": "2023-01-01T00:55:00"}
{"meterId": "98125-2", "measurementInKWh": 15.983856156042478, "zipCode": 98125, "measurementDate": "2023-01-01T00:55:00"}
{"meterId": "98125-3", "measurementInKWh": 7.349306997041319, "zipCode": 98125, "measurementDate": "2023-01-01T00:55:00"}
{"meterId": "98125-4", "measurementInKWh": 15.744910955222236, "zipCode": 98125, "measurementDate": "2023-01-01T00:55:00"}
{"meterId": "98126-1", "measurementInKWh": 16.63983768693724, "zipCode": 98126, "measurementDate": "2023-01-01T00:55:00"}
{"meterId": "98126-2", "measurementInKWh": 11.715015619787254, "zipCode": 98126, "measurementDate": "2023-01-01T00:55:00"}
{"meterId": "98126-3", "measurementInKWh": 16.25774792715198, "zipCode": 98126, "measurementDate": "2023-01-01T00:55:00"}
{"meterId": "98126-4", "measurementInKWh": 7.5314718955851125, "zipCode": 98126, "measurementDate": "2023-01-01T00:55:00"}
{"meterId": "98133-1", "measurementInKWh": 13.930339841314671, "zipCode": 98133, "measurementDate": "2023-01-01T00:55:00"}
{"meterId": "98133-2", "measurementInKWh": 17.835378539544507, "zipCode": 98133, "measurementDate": "2023-01-01T00:55:00"}
{"meterId": "98133-3", "measurementInKWh": 9.251475281882755, "zipCode": 98133, "measurementDate": "2023-01-01T00:55:00"}
{"meterId": "98133-4", "measurementInKWh": 12.746721984272018, "zipCode": 98133, "measurementDate": "2023-01-01T00:55:00"}
{"meterId": "98134-1", "measurementInKWh": 7.388029275473072, "zipCode": 98134, "measurementDate": "2023-01-01T00:55:00"}
{"meterId": "98134-2", "measurementInKWh": 18.698310884139232, "zipCode": 98134, "measurementDate": "2023-01-01T00:55:00"}
{"meterId": "98134-3", "measurementInKWh": 9.089008880453669, "zipCode": 98134, "measurementDate": "2023-01-01T00:55:00"}
{"meterId": "98134-4", "measurementInKWh": 8.245044097015743, "zipCode": 98134, "measurementDate": "2023-01-01T00:55:00"}
{"meterId": "98136-1", "measurementInKWh": 10.571228418979484, "zipCode": 98136, "measurementDate": "2023-01-01T00:55:00"}
{"meterId": "98136-2", "measurementInKWh": 12.517223872935606, "zipCode": 98136, "measurementDate": "2023-01-01T00:55:00"}
{"meterId": "98136-3", "measurementInKWh": 13.955170595911309, "zipCode": 98136, "measurementDate": "2023-01-01T00:55:00"}
{"meterId": "98136-4", "measurementInKWh": 13.092502274640072, "zipCode": 98136, "measurementDate": "2023-01-01T00:55:00"}
{"meterId": "98144-1", "measurementInKWh": 8.202194038546436, "zipCode": 98144, "measurementDate": "2023-01-01T00:55:00"}
{"meterId": "98144-2", "measurementInKWh": 17.601326641826105, "zipCode": 98144, "measurementDate": "2023-01-01T00:55:00"}
{"meterId": "98144-3", "measurementInKWh": 7.199098065991442, "zipCode": 98144, "measurementDate": "2023-01-01T00:55:00"}
{"meterId": "98144-4", "measurementInKWh": 11.765776556287994, "zipCode": 98144, "measurementDate": "2023-01-01T00:55:00"}
{"meterId": "98146-1", "measurementInKWh": 9.827973327950257, "zipCode": 98146, "measurementDate": "2023-01-01T00:55:00"}
{"meterId": "98146-2", "measurementInKWh": 13.177725990999813, "zipCode": 98146, "measurementDate": "2023-01-01T00:55:00"}
{"meterId": "98146-3", "measurementInKWh": 15.519541486807112, "zipCode": 98146, "measurementDate": "2023-01-01T00:55:00"}
{"meterId": "98146-4", "measurementInKWh": 12.436287125963544, "zipCode": 98146, "measurementDate": "2023-01-01T00:55:00"}
{"meterId": "98148-1", "measurementInKWh": 17.86168291392019, "zipCode": 98148, "measurementDate": "2023-01-01T00:55:00"}
{"meterId": "98148-2", "measurementInKWh": 9.346437019105498, "zipCode": 98148, "measurementDate": "2023-01-01T00:55:00"}
{"meterId": "98148-3", "measurementInKWh": 18.984045986103613, "zipCode": 98148, "measurementDate": "2023-01-01T00:55:00"}
{"meterId": "98148-4", "measurementInKWh": 10.09744289896041, "zipCode": 98148, "measurementDate": "2023-01-01T00:55:00"}
{"meterId": "98154-1", "measurementInKWh": 15.13888475001651, "zipCode": 98154, "measurementDate": "2023-01-01T00:55:00"}
{"meterId": "98154-2", "measurementInKWh": 16.073567450436983, "zipCode": 98154, "measurementDate": "2023-01-01T00:55:00"}
{"meterId": "98154-3", "measurementInKWh": 10.079792596654602, "zipCode": 98154, "measurementDate": "2023-01-01T00:55:00"}
{"meterId": "98154-4", "measurementInKWh": 7.703293984669656, "zipCode": 98154, "measurementDate": "2023-01-01T00:55:00"}
{"meterId": "98155-1", "measurementInKWh": 14.095293598148931, "zipCode": 98155, "measurementDate": "2023-01-01T00:55:00"}
{"meterId": "98155-2", "measurementInKWh": 17.145611301489197, "zipCode": 98155, "measurementDate": "2023-01-01T00:55:00"}
{"meterId": "98155-3", "measurementInKWh": 7.969909409429536, "zipCode": 98155, "measurementDate": "2023-01-01T00:55:00"}
{"meterId": "98155-4", "measurementInKWh": 14.200290826612743, "zipCode": 98155, "measurementDate": "2023-01-01T00:55:00"}
{"meterId": "98125-1", "measurementInKWh": 17.256161498760086, "zipCode": 98125, "measurementDate": "2023-01-01T01:00:00"}
{"meterId": "98125-2", "measurementInKWh": 9.068359447918427, "zipCode": 98125, "measurementDate": "2023-01-01T01:00:00"}
{"meterId": "98125-3", "measurementInKWh": 11.878797518565136, "zipCode": 98125, "measurementDate": "2023-01-01T01:00:00"}
{"meterId": "98125-4", "measurementInKWh": 13.620184061925059, "zipCode": 98125, "measurementDate": "2023-01-01T01:00:00"}
{"meterId": "98126-1", "measurementInKWh": 8.524327153552186, "zipCode": 98126, "measurementDate": "2023-01-01T01:00:00"}
{"meterId": "98126-2", "measurementInKWh": 5.655361780220221, "zipCode": 98126, "measurementDate": "2023-01-01T01:00:00"}
{"meterId": "98126-3", "measurementInKWh": 8.220265735551774, "zipCode": 98126, "measurementDate": "2023-01-01T01:00:00"}
{"meterId": "98126-4", "measurementInKWh": 16.32751341191232, "zipCode": 98126, "measurementDate": "2023-01-01T01:00:00"}
{"meterId": "98133-1", "measurementInKWh": 16.980918264313146, "zipCode": 98133, "measurementDate": "2023-01-01T01:00:00"}
{"meterId": "98133-2", "measurementInKWh": 6.1456455591117845, "zipCode": 98133, "measurementDate": "2023-01-01T01:00:00"}
{"meterId": "98133-3", "measurementInKWh": 5.221719267042873, "zipCode": 98133, "measurementDate": "2023-01-01T01:00:00"}
{"meterId": "98133-4", "measurementInKWh": 10.894635487818348, "zipCode": 98133, "measurementDate": "2023-01-01T01:00:00"}
{"meterId": "98134-1", "measurementInKWh": 8.40115925240412, "zipCode": 98134, "measurementDate": "2023-01-01T01:00:00"}
{"meterId": "98134-2", "measurementInKWh": 8.430068752648175, "zipCode": 98134, "measurementDate": "2023-01-01T01:00:00"}
{"meterId": "98134-3", "measurementInKWh": 13.9542957435269, "zipCode": 98134, "measurementDate": "2023-01-01T01:00:00"}
{"meterId": "98134-4", "measurementInKWh": 18.24352976181583, "zipCode": 98134, "measurementDate": "2023-01-01T01:00:00"}
{"meterId": "98136-1", "measurementInKWh": 8.38617623810065, "zipCode": 98136, "measurementDate": "2023-01-01T01:00:00"}
{"meterId": "98136-2", "measurementInKWh": 17.7457999652102, "zipCode": 98136, "measurementDate": "2023-01-01T01:00:00"}
{"meterId": "98136-3", "measurementInKWh": 15.270774257186295, "zipCode": 98136, "measurementDate": "2023-01-01T01:00:00"}
{"meterId": "98136-4", "measurementInKWh": 7.355765404324808, "zipCode": 98136, "measurementDate": "2023-01-01T01:00:00"}
{"meterId": "98144-1", "measurementInKWh": 12.784798038776442, "zipCode": 98144, "measurementDate": "2023-01-01T01:00:00"}
{"meterId": "98144-2", "measurementInKWh": 18.85956338702851, "zipCode": 98144, "measurementDate": "2023-01-01T01:00:00"}
{"meterId": "98144-3", "measurementInKWh": 7.641978593841827, "zipCode": 98144, "measurementDate": "2023-01-01T01:00:00"}
{"meterId": "98144-4", "measurementInKWh": 9.136209036861441, "zipCode": 98144, "measurementDate": "2023-01-01T01:00:00"}
{"meterId": "98146-1", "measurementInKWh": 5.748349288915295, "zipCode": 98146, "measurementDate": "2023-01-01T01:00:00"}
{"meterId": "98146-2", "measurementInKWh": 10.233569498918904, "zipCode": 98146, "measurementDate": "2023-01-01T01:00:00"}
{"meterId": "98146-3", "measurementInKWh": 19.847945542548423, "zipCode": 98146, "measurementDate": "2023-01-01T01:00:00"}
{"meterId": "98146-4", "measurementInKWh": 17.887790945895357, "zipCode": 98146, "measurementDate": "2023-01-01T01:00:00"}
{"meterId": "98148-1", "measurementInKWh": 16.255875428209592, "zipCode": 98148, "measurementDate": "2023-01-01T01:00:00"}
{"meterId": "98148-2", "measurementInKWh": 19.835640789293116, "zipCode": 98148, "measurementDate": "2023-01-01T01:00:00"}
{"meterId": "98148-3", "measurementInKWh": 17.183380768786556, "zipCode": 98148, "measurementDate": "2023-01-01T01:00:00"}
{"meterId": "98148-4", "measurementInKWh": 13.313260890487646, "zipCode": 98148, "measurementDate": "2023-01-01T01:00:00"}
{"meterId": "98154-1", "measurementInKWh": 7.748243481661825, "zipCode": 98154, "measurementDate": "2023-01-01T01:00:00"}
{"meterId": "98154-2", "measurementInKWh": 19.361924036196022, "zipCode": 98154, "measurementDate": "2023-01-01T01:00:00"}
{"meterId": "98154-3", "measurementInKWh": 11.934206692441613, "zipCode": 98154, "measurementDate": "2023-01-01T01:00:00"}
{"meterId": "98154-4", "measurementInKWh": 11.190186154726948, "zipCode": 98154, "measurementDate": "2023-01-01T01:00:00"}
{"meterId": "98155-1", "measurementInKWh": 9.102715172274419, "zipCode": 98155, "measurementDate": "2023-01-01T01:00:00"}
{"meterId": "98155-2", "measurementInKWh": 8.260765430069274, "zipCode": 98155, "measurementDate": "2023-01-01T01:00:00"}
{"meterId": "98155-3", "measurementInKWh": 6.552904090119567, "zipCode": 98155, "measurementDate": "2023-01-01T01:00:00"}
{"meterId": "98155-4", "measurementInKWh": 15.840016912075946, "zipCode": 98155, "measurementDate": "2023-01-01T01:00:00"}