{"meterId": "98125-1", "measurementInKWh": 15.155643699662734, "zipCode": 98125, "measurementDate": "2023-01-01T00:05:00"}
{"meterId": "98125-2", "measurementInKWh": 18.267466842080893, "zipCode": 98125, "measurementDate": "2023-01-01T00:05:00"}
{"meterId": "98125-3", "measurementInKWh": 13.732474632910531, "zipCode": 98125, "measurementDate": "2023-01-01T00:05:00"}
{"meterId": "98125-4", "measurementInKWh": 18.145359062333977, "zipCode": 98125, "measurementDate": "2023-01-01T00:05:00"}
{"meterId": "98126-1", "measurementInKWh": 11.631953293155332, "zipCode": 98126, "measurementDate": "2023-01-01T00:05:00"}
{"meterId": "98126-2", "measurementInKWh": 7.349980260724479, "zipCode": 98126, "measurementDate": "2023-01-01T00:05:00"}
{"meterId": "98126-3", "measurementInKWh": 8.751897627855453, "zipCode": 98126, "measurementDate": "2023-01-01T00:05:00"}
{"meterId": "98126-4", "measurementInKWh": 6.050510120535444, "zipCode": 98126, "measurementDate": "2023-01-01T00:05:00"}
{"meterId": "98133-1", "measurementInKWh": 6.220189235536566, "zipCode": 98133, "measurementDate": "2023-01-01T00:05:00"}
{"meterId": "98133-2", "measurementInKWh": 17.200036564341026, "zipCode": 98133, "measurementDate": "2023-01-01T00:05:00"}
{"meterId": "98133-3", "measurementInKWh": 11.922609073256396, "zipCode": 98133, "measurementDate": "2023-01-01T00:05:00"}
{"meterId": "98133-4", "measurementInKWh": 11.573860854347059, "zipCode": 98133, "measurementDate": "2023-01-01T00:05:00"}
{"meterId": "98134-1", "measurementInKWh": 17.077167642369048, "zipCode": 98134, "measurementDate": "2023-01-01T00:05:00"}
{"meterId": "98134-2", "measurementInKWh": 18.227436511642875, "zipCode": 98134, "measurementDate": "2023-01-01T00:05:00"}
{"meterId": "98134-3", "measurementInKWh": 12.580815133954696, "zipCode": 98134, "measurementDate": "2023-01-01T00:05:00"}
{"meterId": "98134-4", "measurementInKWh": 8.47832478098325, "zipCode": 98134, "measurementDate": "2023-01-01T00:05:00"}
{"meterId": "98136-1", "measurementInKWh": 15.019791961140486, "zipCode": 98136, "measurementDate": "2023-01-01T00:05:00"}
{"meterId": "98136-2", "measurementInKWh": 12.304714417363595, "zipCode": 98136, "measurementDate": "2023-01-01T00:05:00"}
{"meterId": "98136-3", "measurementInKWh": 15.426947551328483, "zipCode": 98136, "measurementDate": "2023-01-01T00:05:00"}
{"meterId": "98136-4", "measurementInKWh": 9.646317000557474, "zipCode": 98136, "measurementDate": "2023-01-01T00:05:00"}
{"meterId": "98144-1", "measurementInKWh": 9.12267701146295, "zipCode": 98144, "measurementDate": "2023-01-01T00:05:00"}
{"meterId": "98144-2", "measurementInKWh": 12.367002731885727, "zipCode": 98144, "measurementDate": "2023-01-01T00:05:00"}
{"meterId": "98144-3", "measurementInKWh": 6.9988655299038465, "zipCode": 98144, "measurementDate": "2023-01-01T00:05:00"}
{"meterId": "98144-4", "measurementInKWh": 10.976067589245538, "zipCode": 98144, "measurementDate": "2023-01-01T00:05:00"}
{"meterId": "98146-1", "measurementInKWh": 17.070894272192188, "zipCode": 98146, "measurementDate": "2023-01-01T00:05:00"}
{"meterId": "98146-2", "measurementInKWh": 19.767588252423362, "zipCode": 98146, "measurementDate": "2023-01-01T00:05:00"}
{"meterId": "98146-3", "measurementInKWh": 18.309806433166997, "zipCode": 98146, "measurementDate": "2023-01-01T00:05:00"}
{"meterId": "98146-4", "measurementInKWh": 16.150486704227887, "zipCode": 98146, "measurementDate": "2023-01-01T00:05:00"}
{"meterId": "98148-1", "measurementInKWh": 10.87299845328769, "zipCode": 98148, "measurementDate": "2023-01-01T00:05:00"}
{"meterId": "98148-2", "measurementInKWh": 6.741228784183781, "zipCode": 98148, "measurementDate": "2023-01-01T00:05:00"}
{"meterId": "98148-3", "measurementInKWh": 19.72312333746487, "zipCode": 98148, "measurementDate": "2023-01-01T00:05:00"}
{"meterId": "98148-4", "measurementInKWh": 12.918308531875546, "zipCode": 98148, "measurementDate": "2023-01-01T00:05:00"}
{"meterId": "98154-1", "measurementInKWh": 5.156201849349863, "zipCode": 98154, "measurementDate": "2023-01-01T00:05:00"}
{"meterId": "98154-2", "measurementInKWh": 10.793318305729576, "zipCode": 98154, "measurementDate": "2023-01-01T00:05:00"}
{"meterId": "98154-3", "measurementInKWh": 8.066068937261797, "zipCode": 98154, "measurementDate": "2023-01-01T00:05:00"}
{"meterId": "98154-4", "measurementInKWh": 14.3264136605543, "zipCode": 98154, "measurementDate": "2023-01-01T00:05:00"}
{"meterId": "98155-1", "measurementInKWh": 16.748311418926086, "zipCode": 98155, "measurementDate": "2023-01-01T00:05:00"}
{"meterId": "98155-2", "measurementInKWh": 16.666681864730908, "zipCode": 98155, "measurementDate": "2023-01-01T00:05:00"}
{"meterId": "98155-3", "measurementInKWh": 9.262317117575295, "zipCode": 98155, "measurementDate": "2023-01-01T00:05:00"}
{"meterId": "98155-4", "measurementInKWh": 17.28846305545322, "zipCode": 98155, "measurementDate": "2023-01-01T00:05:00"}
{"meterId": "98125-1", "measurementInKWh": 14.949458475181457, "zipCode": 98125, "measurementDate": "2023-01-01T00:10:00"}
{"meterId": "98125-2", "measurementInKWh": 16.281292074196067, "zipCode": 98125, "measurementDate": "2023-01-01T00:10:00"}
{"meterId": "98125-3", "measurementInKWh": 6.395121560126794, "zipCode": 98125, "measurementDate": "2023-01-01T00:10:00"}
{"meterId": "98125-4", "measurementInKWh": 17.726764992072447, "zipCode": 98125, "measurementDate": "2023-01-01T00:10:00"}
{"meterId": "98126-1", "measurementInKWh": 14.836975604607968, "zipCode": 98126, "measurementDate": "2023-01-01T00:10:00"}
{"meterId": "98126-2", "measurementInKWh": 7.245988853715904, "zipCode": 98126, "measurementDate": "2023-01-01T00:10:00"}
{"meterId": "98126-3", "measurementInKWh": 5.198819680444252, "zipCode": 98126, "measurementDate": "2023-01-01T00:10:00"}
{"meterId": "98126-4", "measurementInKWh": 15.588292924740339, "zipCode": 98126, "measurementDate": "2023-01-01T00:10:00"}
{"meterId": "98133-1", "measurementInKWh": 12.21294007388776, "zipCode": 98133, "measurementDate": "2023-01-01T00:10:00"}
{"meterId": "98133-2", "measurementInKWh": 15.211118097789772, "zipCode": 98133, "measurementDate": "2023-01-01T00:10:00"}
{"meterId": "98133-3", "measurementInKWh": 6.246876119598237, "zipCode": 98133, "measurementDate": "2023-01-01T00:10:00"}
{"meterId": "98133-4", "measurementInKWh": 15.20043441997811, "zipCode": 98133, "measurementDate": "2023-01-01T00:10:00"}
{"meterId": "98134-1", "measurementInKWh": 10.092125844477025, "zipCode": 98134, "measurementDate": "2023-01-01T00:10:00"}
{"meterId": "98134-2", "measurementInKWh": 9.844051921642846, "zipCode": 98134, "measurementDate": "2023-01-01T00:10:00"}
{"meterId": "98134-3", "measurementInKWh": 9.11577997692996, "zipCode": 98134, "measurementDate": "2023-01-01T00:10:00"}
{"meterId": "98134-4", "measurementInKWh": 9.863910781805288, "zipCode": 98134, "measurementDate": "2023-01-01T00:10:00"}
{"meterId": "98136-1", "measurementInKWh": 7.111695979085063, "zipCode": 98136, "measurementDate": "2023-01-01T00:10:00"}
{"meterId": "98136-2", "measurementInKWh": 12.940410137212908, "zipCode": 98136, "measurementDate": "2023-01-01T00:10:00"}
{"meterId": "98136-3", "measurementInKWh": 17.880989252226446, "zipCode": 98136, "measurementDate": "2023-01-01T00:10:00"}
{"meterId": "98136-4", "measurementInKWh": 15.083376568188372, "zipCode": 98136, "measurementDate": "2023-01-01T00:10:00"}
{"meterId": "98144-1", "measurementInKWh": 17.219710470831075, "zipCode": 98144, "measurementDate": "2023-01-01T00:10:00"}
{"meterId": "98144-2", "measurementInKWh": 7.253062598922048, "zipCode": 98144, "measurementDate": "2023-01-01T00:10:00"}
{"meterId": "98144-3", "measurementInKWh": 16.8054016230521, "zipCode": 98144, "measurementDate": "2023-01-01T00:10:00"}
{"meterId": "98144-4", "measurementInKWh": 11.029739898389618, "zipCode": 98144, "measurementDate": "2023-01-01T00:10:00"}
{"meterId": "98146-1", "measurementInKWh": 14.031156933582396, "zipCode": 98146, "measurementDate": "2023-01-01T00:10:00"}
{"meterId": "98146-2", "measurementInKWh": 11.957866983000166, "zipCode": 98146, "measurementDate": "2023-01-01T00:10:00"}
{"meterId": "98146-3", "measurementInKWh": 15.25223808722998, "zipCode": 98146, "measurementDate": "2023-01-01T00:10:00"}
{"meterId": "98146-4", "measurementInKWh": 10.270998574152998, "zipCode": 98146, "measurementDate": "2023-01-01T00:10:00"}
{"meterId": "98148-1", "measurementInKWh": 5.909033967045291, "zipCode": 98148, "measurementDate": "2023-01-01T00:10:00"}
{"meterId": "98148-2", "measurementInKWh": 13.315063167846361, "zipCode": 98148, "measurementDate": "2023-01-01T00:10:00"}
{"meterId": "98148-3", "measurementInKWh": 9.594385583322062, "zipCode": 98148, "measurementDate": "2023-01-01T00:10:00"}
{"meterId": "98148-4", "measurementInKWh": 9.39067461939193, "zipCode": 98148, "measurementDate": "2023-01-01T00:10:00"}
{"meterId": "98154-1", "measurementInKWh": 5.789707467939456, "zipCode": 98154, "measurementDate": "2023-01-01T00:10:00"}
{"meterId": "98154-2", "measurementInKWh": 9.299445557485727, "zipCode": 98154, "measurementDate": "2023-01-01T00:10:00"}
{"meterId": "98154-3", "measurementInKWh": 16.31282045229103, "zipCode": 98154, "measurementDate": "2023-01-01T00:10:00"}
{"meterId": "98154-4", "measurementInKWh": 6.468435647314839, "zipCode": 98154, "measurementDate": "2023-01-01T00:10:00"}
{"meterId": "98155-1", "measurementInKWh": 10.613670552219148, "zipCode": 98155, "measurementDate": "2023-01-01T00:10:00"}
{"meterId": "98155-2", "measurementInKWh": 12.254171171408874, "zipCode": 98155, "measurementDate": "2023-01-01T00:10:00"}
{"meterId": "98155-3", "measurementInKWh": 12.808001189242066, "zipCode": 98155, "measurementDate": "2023-01-01T00:10:00"}
{"meterId": "98155-4", "measurementInKWh": 13.6269101129854, "zipCode": 98155, "measurementDate": "2023-01-01T00:10:00"}
{"meterId": "98125-1", "measurementInKWh": 19.18000653731213, "zipCode": 98125, "measurementDate": "2023-01-01T00:15:00"}
{"meterId": "98125-2", "measurementInKWh": 14.696449232531549, "zipCode": 98125, "measurementDate": "2023-01-01T00:15:00"}
{"meterId": "98125-3", "measurementInKWh": 15.935098584179583, "zipCode": 98125, "measurementDate": "2023-01-01T00:15:00"}
{"meterId": "98125-4", "measurementInKWh": 8.456136918018752, "zipCode": 98125, "measurementDate": "2023-01-01T00:15:00"}
{"meterId": "98126-1", "measurementInKWh": 16.944848689295384, "zipCode": 98126, "measurementDate": "2023-01-01T00:15:00"}
{"meterId": "98126-2", "measurementInKWh": 9.349310170401399, "zipCode": 98126, "measurementDate": "2023-01-01T00:15:00"}
{"meterId": "98126-3", "measurementInKWh": 6.785070893686786, "zipCode": 98126, "measurementDate": "2023-01-01T00:15:00"}
{"meterId": "98126-4", "measurementInKWh": 19.966812366918965, "zipCode": 98126, "measurementDate": "2023-01-01T00:15:00"}
{"meterId": "98133-1", "measurementInKWh": 17.547410152078363, "zipCode": 98133, "measurementDate": "2023-01-01T00:15:00"}
{"meterId": "98133-2", "measurementInKWh": 15.195734854058701, "zipCode": 98133, "measurementDate": "2023-01-01T00:15:00"}
{"meterId": "98133-3", "measurementInKWh": 16.754268001158216, "zipCode": 98133, "measurementDate": "2023-01-01T00:15:00"}
{"meterId": "98133-4", "measurementInKWh": 8.796539504944192, "zipCode": 98133, "measurementDate": "2023-01-01T00:15:00"}
{"meterId": "98134-1", "measurementInKWh": 15.484242531571896, "zipCode": 98134, "measurementDate": "2023-01-01T00:15:00"}
{"meterId": "98134-2", "measurementInKWh": 5.883956628534702, "zipCode": 98134, "measurementDate": "2023-01-01T00:15:00"}
{"meterId": "98134-3", "measurementInKWh": 6.1132212496608895, "zipCode": 98134, "measurementDate": "2023-01-01T00:15:00"}
{"meterId": "98134-4", "measurementInKWh": 8.772291525644697, "zipCode": 98134, "measurementDate": "2023-01-01T00:15:00"}
{"meterId": "98136-1", "measurementInKWh": 5.384061275360621, "zipCode": 98136, "measurementDate": "2023-01-01T00:15:00"}
{"meterId": "98136-2", "measurementInKWh": 15.95916368564247, "zipCode": 98136, "measurementDate": "2023-01-01T00:15:00"}
{"meterId": "98136-3", "measurementInKWh": 17.036148296825328, "zipCode": 98136, "measurementDate": "2023-01-01T00:15:00"}
{"meterId": "98136-4", "measurementInKWh": 7.350895409014692, "zipCode": 98136, "measurementDate": "2023-01-01T00:15:00"}
{"meterId": "98144-1", "measurementInKWh": 13.037885112008716, "zipCode": 98144, "measurementDate": "2023-01-01T00:15:00"}
{"meterId": "98144-2", "measurementInKWh": 6.392085732676318, "zipCode": 98144, "measurementDate": "2023-01-01T00:15:00"}
{"meterId": "98144-3", "measurementInKWh": 5.6740196097160265, "zipCode": 98144, "measurementDate": "2023-01-01T00:15:00"}
{"meterId": "98144-4", "measurementInKWh": 14.993321902919519, "zipCode": 98144, "measurementDate": "2023-01-01T00:15:00"}
{"meterId": "98146-1", "measurementInKWh": 13.071157412851665, "zipCode": 98146, "measurementDate": "2023-01-01T00:15:00"}
{"meterId": "98146-2", "measurementInKWh": 17.30159531472187, "zipCode": 98146, "measurementDate": "2023-01-01T00:15:00"}
{"meterId": "98146-3", "measurementInKWh": 19.50649674797438, "zipCode": 98146, "measurementDate": "2023-01-01T00:15:00"}
{"meterId": "98146-4", "measurementInKWh": 14.152724736645046, "zipCode": 98146, "measurementDate": "2023-01-01T00:15:00"}
{"meterId": "98148-1", "measurementInKWh": 5.915313859827788, "zipCode": 98148, "measurementDate": "2023-01-01T00:15:00"}
{"meterId": "98148-2", "measurementInKWh": 11.193910160739946, "zipCode": 98148, "measurementDate": "2023-01-01T00:15:00"}
{"meterId": "98148-3", "measurementInKWh": 14.43429940510539, "zipCode": 98148, "measurementDate": "2023-01-01T00:15:00"}
{"meterId": "98148-4", "measurementInKWh": 15.370850038321501, "zipCode": 98148, "measurementDate": "2023-01-01T00:15:00"}
{"meterId": "98154-1", "measurementInKWh": 18.890480978199566, "zipCode": 98154, "measurementDate": "2023-01-01T00:15:00"}
{"meterId": "98154-2", "measurementInKWh": 12.102067507056931, "zipCode": 98154, "measurementDate": "2023-01-01T00:15:00"}
{"meterId": "98154-3", "measurementInKWh": 15.953156995975824, "zipCode": 98154, "measurementDate": "2023-01-01T00:15:00"}
{"meterId": "98154-4", "measurementInKWh": 8.085366320257235, "zipCode": 98154, "measurementDate": "2023-01-01T00:15:00"}
{"meterId": "98155-1", "measurementInKWh": 14.52162290889087, "zipCode": 98155, "measurementDate": "2023-01-01T00:15:00"}
{"meterId": "98155-2", "measurementInKWh": 17.938526559184034, "zipCode": 98155, "measurementDate": "2023-01-01T00:15:00"}
{"meterId": "98155-3", "measurementInKWh": 17.454546725735963, "zipCode": 98155, "measurementDate": "2023-01-01T00:15:00"}
{"meterId": "98155-4", "measurementInKWh": 16.909491096518106, "zipCode": 98155, "measurementDate": "2023-01-01T00:15:00"}