{"meterId": "98158-1", "measurementInKWh": 9.607883570167598, "zipCode": 98158, "measurementDate": "2023-01-01T00:20:00"}
{"meterId": "98158-2", "measurementInKWh": 9.789043914868481, "zipCode": 98158, "measurementDate": "2023-01-01T00:20:00"}
{"meterId": "98158-3", "measurementInKWh": 14.616370474175822, "zipCode": 98158, "measurementDate": "2023-01-01T00:20:00"}
{"meterId": "98158-4", "measurementInKWh": 10.028705012684568, "zipCode": 98158, "measurementDate": "2023-01-01T00:20:00"}
{"meterId": "98164-1", "measurementInKWh": 6.640297553710022, "zipCode": 98164, "measurementDate": "2023-01-01T00:20:00"}
{"meterId": "98164-2", "measurementInKWh": 16.428996755458094, "zipCode": 98164, "measurementDate": "2023-01-01T00:20:00"}
{"meterId": "98164-3", "measurementInKWh": 16.795813133204888, "zipCode": 98164, "measurementDate": "2023-01-01T00:20:00"}
{"meterId": "98164-4", "measurementInKWh": 6.4742375486021935, "zipCode": 98164, "measurementDate": "2023-01-01T00:20:00"}
{"meterId": "98166-1", "measurementInKWh": 10.133084782889968, "zipCode": 98166, "measurementDate": "2023-01-01T00:20:00"}
{"meterId": "98166-2", "measurementInKWh": 16.903466155410644, "zipCode": 98166, "measurementDate": "2023-01-01T00:20:00"}
{"meterId": "98166-3", "measurementInKWh": 14.19164026570023, "zipCode": 98166, "measurementDate": "2023-01-01T00:20:00"}
{"meterId": "98166-4", "measurementInKWh": 14.894260406383784, "zipCode": 98166, "measurementDate": "2023-01-01T00:20:00"}
{"meterId": "98168-1", "measurementInKWh": 9.227992827200062, "zipCode": 98168, "measurementDate": "2023-01-01T00:20:00"}
{"meterId": "98168-2", "measurementInKWh": 14.386283606447106, "zipCode": 98168, "measurementDate": "2023-01-01T00:20:00"}
{"meterId": "98168-3", "measurementInKWh": 10.962962707805952, "zipCode": 98168, "measurementDate": "2023-01-01T00:20:00"}
{"meterId": "98168-4", "measurementInKWh": 5.517806621878977, "zipCode": 98168, "measurementDate": "2023-01-01T00:20:00"}
{"meterId": "98174-1", "measurementInKWh": 15.992188732210387, "zipCode": 98174, "measurementDate": "2023-01-01T00:20:00"}
{"meterId": "98174-2", "measurementInKWh": 6.732237215372026, "zipCode": 98174, "measurementDate": "2023-01-01T00:20:00"}
{"meterId": "98174-3", "measurementInKWh": 9.586028943827083, "zipCode": 98174, "measurementDate": "2023-01-01T00:20:00"}
{"meterId": "98174-4", "measurementInKWh": 15.041548697163348, "zipCode": 98174, "measurementDate": "2023-01-01T00:20:00"}
{"meterId": "98177-1", "measurementInKWh": 12.71906011048533, "zipCode": 98177, "measurementDate": "2023-01-01T00:20:00"}
{"meterId": "98177-2", "measurementInKWh": 19.3429985507431, "zipCode": 98177, "measurementDate": "2023-01-01T00:20:00"}
{"meterId": "98177-3", "measurementInKWh": 15.162004126095027, "zipCode": 98177, "measurementDate": "2023-01-01T00:20:00"}
{"meterId": "98177-4", "measurementInKWh": 18.31998282348608, "zipCode": 98177, "measurementDate": "2023-01-01T00:20:00"}
{"meterId": "98178-1", "measurementInKWh": 12.425464340918738, "zipCode": 98178, "measurementDate": "2023-01-01T00:20:00"}
{"meterId": "98178-2", "measurementInKWh": 9.53811629161632, "zipCode": 98178, "measurementDate": "2023-01-01T00:20:00"}
{"meterId": "98178-3", "measurementInKWh": 5.216743001910457, "zipCode": 98178, "measurementDate": "2023-01-01T00:20:00"}
{"meterId": "98178-4", "measurementInKWh": 11.469288335935973, "zipCode": 98178, "measurementDate": "2023-01-01T00:20:00"}
{"meterId": "98188-1", "measurementInKWh": 11.818906325101645, "zipCode": 98188, "measurementDate": "2023-01-01T00:20:00"}
{"meterId": "98188-2", "measurementInKWh": 12.32138422734105, "zipCode": 98188, "measurementDate": "2023-01-01T00:20:00"}
{"meterId": "98188-3", "measurementInKWh": 14.522945972368786, "zipCode": 98188, "measurementDate": "2023-01-01T00:20:00"}
{"meterId": "98188-4", "measurementInKWh": 16.83406928256747, "zipCode": 98188, "measurementDate": "2023-01-01T00:20:00"}
{"meterId": "98198-1", "measurementInKWh": 12.440023567892613, "zipCode": 98198, "measurementDate": "2023-01-01T00:20:00"}
{"meterId": "98198-2", "measurementInKWh": 16.357375348990818, "zipCode": 98198, "measurementDate": "2023-01-01T00:20:00"}
{"meterId": "98198-3", "measurementInKWh": 11.675694646760984, "zipCode": 98198, "measurementDate": "2023-01-01T00:20:00"}
{"meterId": "98198-4", "measurementInKWh": 19.195036043260888, "zipCode": 98198, "measurementDate": "2023-01-01T00:20:00"}
{"meterId": "98199-1", "measurementInKWh": 19.274531965766574, "zipCode": 98199, "measurementDate": "2023-01-01T00:20:00"}
{"meterId": "98199-2", "measurementInKWh": 7.0674402595424475, "zipCode": 98199, "measurementDate": "2023-01-01T00:20:00"}
{"meterId": "98199-3", "measurementInKWh": 11.303178357441215, "zipCode": 98199, "measurementDate": "2023-01-01T00:20:00"}
{"meterId": "98199-4", "measurementInKWh": 19.008039714257805, "zipCode": 98199, "measurementDate": "2023-01-01T00:20:00"}
{"meterId": "98158-1", "measurementInKWh": 14.261626099020475, "zipCode": 98158, "measurementDate": "2023-01-01T00:25:00"}
{"meterId": "98158-2", "measurementInKWh": 15.84946941908813, "zipCode": 98158, "measurementDate": "2023-01-01T00:25:00"}
{"meterId": "98158-3", "measurementInKWh": 19.140285053730285, "zipCode": 98158, "measurementDate": "2023-01-01T00:25:00"}
{"meterId": "98158-4", "measurementInKWh": 6.195305615229136, "zipCode": 98158, "measurementDate": "2023-01-01T00:25:00"}
{"meterId": "98164-1", "measurementInKWh": 10.586231068050104, "zipCode": 98164, "measurementDate": "2023-01-01T00:25:00"}
{"meterId": "98164-2", "measurementInKWh": 11.816342721692948, "zipCode": 98164, "measurementDate": "2023-01-01T00:25:00"}
{"meterId": "98164-3", "measurementInKWh": 10.950073447064431, "zipCode": 98164, "measurementDate": "2023-01-01T00:25:00"}
{"meterId": "98164-4", "measurementInKWh": 6.945785444544653, "zipCode": 98164, "measurementDate": "2023-01-01T00:25:00"}
{"meterId": "98166-1", "measurementInKWh": 15.828519803140384, "zipCode": 98166, "measurementDate": "2023-01-01T00:25:00"}
{"meterId": "98166-2", "measurementInKWh": 13.48007614096581, "zipCode": 98166, "measurementDate": "2023-01-01T00:25:00"}
{"meterId": "98166-3", "measurementInKWh": 9.832122219945099, "zipCode": 98166, "measurementDate": "2023-01-01T00:25:00"}
{"meterId": "98166-4", "measurementInKWh": 6.556856215741034, "zipCode": 98166, "measurementDate": "2023-01-01T00:25:00"}
{"meterId": "98168-1", "measurementInKWh": 19.62976382355162, "zipCode": 98168, "measurementDate": "2023-01-01T00:25:00"}
{"meterId": "98168-2", "measurementInKWh": 16.90004933117871, "zipCode": 98168, "measurementDate": "2023-01-01T00:25:00"}
{"meterId": "98168-3", "measurementInKWh": 12.332712915725033, "zipCode": 98168, "measurementDate": "2023-01-01T00:25:00"}
{"meterId": "98168-4", "measurementInKWh": 8.72255327565765, "zipCode": 98168, "measurementDate": "2023-01-01T00:25:00"}
{"meterId": "98174-1", "measurementInKWh": 10.628065307285802, "zipCode": 98174, "measurementDate": "2023-01-01T00:25:00"}
{"meterId": "98174-2", "measurementInKWh": 5.481472194131066, "zipCode": 98174, "measurementDate": "2023-01-01T00:25:00"}
{"meterId": "98174-3", "measurementInKWh": 8.490571586695156, "zipCode": 98174, "measurementDate": "2023-01-01T00:25:00"}
{"meterId": "98174-4", "measurementInKWh": 17.94353812989335, "zipCode": 98174, "measurementDate": "2023-01-01T00:25:00"}
{"meterId": "98177-1", "measurementInKWh": 16.90148373701085, "zipCode": 98177, "measurementDate": "2023-01-01T00:25:00"}
{"meterId": "98177-2", "measurementInKWh": 19.279131164422623, "zipCode": 98177, "measurementDate": "2023-01-01T00:25:00"}
{"meterId": "98177-3", "measurementInKWh": 6.77382975297502, "zipCode": 98177, "measurementDate": "2023-01-01T00:25:00"}
{"meterId": "98177-4", "measurementInKWh": 10.410682369628217, "zipCode": 98177, "measurementDate": "2023-01-01T00:25:00"}
{"meterId": "98178-1", "measurementInKWh": 9.256360365810103, "zipCode": 98178, "measurementDate": "2023-01-01T00:25:00"}
{"meterId": "98178-2", "measurementInKWh": 12.38135343733062, "zipCode": 98178, "measurementDate": "2023-01-01T00:25:00"}
{"meterId": "98178-3", "measurementInKWh": 8.721958959026903, "zipCode": 98178, "measurementDate": "2023-01-01T00:25:00"}
{"meterId": "98178-4", "measurementInKWh": 15.135356058770428, "zipCode": 98178, "measurementDate": "2023-01-01T00:25:00"}
{"meterId": "98188-1", "measurementInKWh": 6.826367248362987, "zipCode": 98188, "measurementDate": "2023-01-01T00:25:00"}
{"meterId": "98188-2", "measurementInKWh": 7.965566866707633, "zipCode": 98188, "measurementDate": "2023-01-01T00:25:00"}
{"meterId": "98188-3", "measurementInKWh": 11.353897168519463, "zipCode": 98188, "measurementDate": "2023-01-01T00:25:00"}
{"meterId": "98188-4", "measurementInKWh": 11.573996819027114, "zipCode": 98188, "measurementDate": "2023-01-01T00:25:00"}
{"meterId": "98198-1", "measurementInKWh": 15.902724062154487, "zipCode": 98198, "measurementDate": "2023-01-01T00:25:00"}
{"meterId": "98198-2", "measurementInKWh": 9.537408009771923, "zipCode": 98198, "measurementDate": "2023-01-01T00:25:00"}
{"meterId": "98198-3", "measurementInKWh": 13.869997492057491, "zipCode": 98198, "measurementDate": "2023-01-01T00:25:00"}
{"meterId": "98198-4", "measurementInKWh": 12.144685788557664, "zipCode": 98198, "measurementDate": "2023-01-01T00:25:00"}
{"meterId": "98199-1", "measurementInKWh": 15.783598397782027, "zipCode": 98199, "measurementDate": "2023-01-01T00:25:00"}
{"meterId": "98199-2", "measurementInKWh": 11.758925075274071, "zipCode": 98199, "measurementDate": "2023-01-01T00:25:00"}
{"meterId": "98199-3", "measurementInKWh": 15.66900179991518, "zipCode": 98199, "measurementDate": "2023-01-01T00:25:00"}
{"meterId": "98199-4", "measurementInKWh": 19.402563441422686, "zipCode": 98199, "measurementDate": "2023-01-01T00:25:00"}
{"meterId": "98158-1", "measurementInKWh": 8.442853780789196, "zipCode": 98158, "measurementDate": "2023-01-01T00:30:00"}
{"meterId": "98158-2", "measurementInKWh": 8.042497476603158, "zipCode": 98158, "measurementDate": "2023-01-01T00:30:00"}
{"meterId": "98158-3", "measurementInKWh": 16.041565940798737, "zipCode": 98158, "measurementDate": "2023-01-01T00:30:00"}
{"meterId": "98158-4", "measurementInKWh": 14.963290603430124, "zipCode": 98158, "measurementDate": "2023-01-01T00:30:00"}
{"meterId": "98164-1", "measurementInKWh": 13.739531285963182, "zipCode": 98164, "measurementDate": "2023-01-01T00:30:00"}
{"meterId": "98164-2", "measurementInKWh": 15.726547871994038, "zipCode": 98164, "measurementDate": "2023-01-01T00:30:00"}
{"meterId": "98164-3", "measurementInKWh": 10.854672239519974, "zipCode": 98164, "measurementDate": "2023-01-01T00:30:00"}
{"meterId": "98164-4", "measurementInKWh": 10.82511997893404, "zipCode": 98164, "measurementDate": "2023-01-01T00:30:00"}
{"meterId": "98166-1", "measurementInKWh": 17.471262728122444, "zipCode": 98166, "measurementDate": "2023-01-01T00:30:00"}
{"meterId": "98166-2", "measurementInKWh": 6.864896310757514, "zipCode": 98166, "measurementDate": "2023-01-01T00:30:00"}
{"meterId": "98166-3", "measurementInKWh": 12.36444439009161, "zipCode": 98166, "measurementDate": "2023-01-01T00:30:00"}
{"meterId": "98166-4", "measurementInKWh": 11.227537391006294, "zipCode": 98166, "measurementDate": "2023-01-01T00:30:00"}
{"meterId": "98168-1", "measurementInKWh": 18.159849781310033, "zipCode": 98168, "measurementDate": "2023-01-01T00:30:00"}
{"meterId": "98168-2", "measurementInKWh": 16.05511232862571, "zipCode": 98168, "measurementDate": "2023-01-01T00:30:00"}
{"meterId": "98168-3", "measurementInKWh": 6.357347542951159, "zipCode": 98168, "measurementDate": "2023-01-01T00:30:00"}
{"meterId": "98168-4", "measurementInKWh": 10.928881624976002, "zipCode": 98168, "measurementDate": "2023-01-01T00:30:00"}
{"meterId": "98174-1", "measurementInKWh": 13.736580211144016, "zipCode": 98174, "measurementDate": "2023-01-01T00:30:00"}
{"meterId": "98174-2", "measurementInKWh": 12.631665614048122, "zipCode": 98174, "measurementDate": "2023-01-01T00:30:00"}
{"meterId": "98174-3", "measurementInKWh": 5.58498502373981, "zipCode": 98174, "measurementDate": "2023-01-01T00:30:00"}
{"meterId": "98174-4", "measurementInKWh": 14.788698885038679, "zipCode": 98174, "measurementDate": "2023-01-01T00:30:00"}
{"meterId": "98177-1", "measurementInKWh": 12.658117645370432, "zipCode": 98177, "measurementDate": "2023-01-01T00:30:00"}
{"meterId": "98177-2", "measurementInKWh": 19.276317773380367, "zipCode": 98177, "measurementDate": "2023-01-01T00:30:00"}
{"meterId": "98177-3", "measurementInKWh": 11.417872743044555, "zipCode": 98177, "measurementDate": "2023-01-01T00:30:00"}
{"meterId": "98177-4", "measurementInKWh": 5.541544768725444, "zipCode": 98177, "measurementDate": "2023-01-01T00:30:00"}
{"meterId": "98178-1", "measurementInKWh": 14.67387910080464, "zipCode": 98178, "measurementDate": "2023-01-01T00:30:00"}
{"meterId": "98178-2", "measurementInKWh": 12.426791076227122, "zipCode": 98178, "measurementDate": "2023-01-01T00:30:00"}
{"meterId": "98178-3", "measurementInKWh": 19.33862097674061, "zipCode": 98178, "measurementDate": "2023-01-01T00:30:00"}
{"meterId": "98178-4", "measurementInKWh": 16.274295293227674, "zipCode": 98178, "measurementDate": "2023-01-01T00:30:00"}
{"meterId": "98188-1", "measurementInKWh": 8.794842558209183, "zipCode": 98188, "measurementDate": "2023-01-01T00:30:00"}
{"meterId": "98188-2", "measurementInKWh": 16.75158752369189, "zipCode": 98188, "measurementDate": "2023-01-01T00:30:00"}
{"meterId": "98188-3", "measurementInKWh": 13.652589154362747, "zipCode": 98188, "measurementDate": "2023-01-01T00:30:00"}
{"meterId": "98188-4", "measurementInKWh": 15.500179586127047, "zipCode": 98188, "measurementDate": "2023-01-01T00:30:00"}
{"meterId": "98198-1", "measurementInKWh": 16.773645952295247, "zipCode": 98198, "measurementDate": "2023-01-01T00:30:00"}
{"meterId": "98198-2", "measurementInKWh": 13.314569064645845, "zipCode": 98198, "measurementDate": "2023-01-01T00:30:00"}
{"meterId": "98198-3", "measurementInKWh": 5.870261089440092, "zipCode": 98198, "measurementDate": "2023-01-01T00:30:00"}
{"meterId": "98198-4", "measurementInKWh": 16.847739766679325, "zipCode": 98198, "measurementDate": "2023-01-01T00:30:00"}
{"meterId": "98199-1", "measurementInKWh": 7.589420243102021, "zipCode": 98199, "measurementDate": "2023-01-01T00:30:00"}
{"meterId": "98199-2", "measurementInKWh": 10.251379718940322, "zipCode": 98199, "measurementDate": "2023-01-01T00:30:00"}
{"meterId": "98199-3", "measurementInKWh": 9.048763313026885, "zipCode": 98199, "measurementDate": "2023-01-01T00:30:00"}
{"meterId": "98199-4", "measurementInKWh": 14.739974213856087, "zipCode": 98199, "measurementDate": "2023-01-01T00:30:00"}